ch2/__init__.py
ch2/__main__.py
ch2/names.py
ch2/commands/__init__.py
ch2/commands/args.py
ch2/commands/constants.py
ch2/commands/db.py
ch2/commands/delete.py
ch2/commands/fit.py
ch2/commands/fix_fit.py
ch2/commands/help.py
ch2/commands/import_.py
ch2/commands/kit.py
ch2/commands/package_fit_profile.py
ch2/commands/process.py
ch2/commands/search.py
ch2/commands/show_schedule.py
ch2/commands/sparkline.py
ch2/commands/thumbnail.py
ch2/commands/upload.py
ch2/commands/validate.py
ch2/commands/web.py
ch2/common/__init__.py
ch2/common/args.py
ch2/common/config.py
ch2/common/date.py
ch2/common/db.py
ch2/common/geo.py
ch2/common/global_.py
ch2/common/io.py
ch2/common/log.py
ch2/common/math.py
ch2/common/md.py
ch2/common/names.py
ch2/common/plot.py
ch2/common/sql.py
ch2/common/user.py
ch2/config/__init__.py
ch2/config/climb.py
ch2/config/database.py
ch2/config/impulse.py
ch2/config/power.py
ch2/config/profile.py
ch2/config/plan/__init__.py
ch2/config/plan/british.py
ch2/config/plan/exponential.py
ch2/config/plan/lib.py
ch2/config/plan/weekly.py
ch2/config/profiles/__init__.py
ch2/config/profiles/acooke.py
ch2/config/profiles/default.py
ch2/data/__init__.py
ch2/data/activity.py
ch2/data/climb.py
ch2/data/cluster.py
ch2/data/coasting.py
ch2/data/constraint.py
ch2/data/elevation.py
ch2/data/fit.py
ch2/data/frame.py
ch2/data/heart_rate.py
ch2/data/impulse.py
ch2/data/lib.py
ch2/data/power.py
ch2/data/query.py
ch2/data/response.py
ch2/data/sector.py
ch2/data/plot/__init__.py
ch2/data/plot/box.py
ch2/data/plot/calendar.py
ch2/data/plot/health.py
ch2/data/plot/line.py
ch2/data/plot/utils.py
ch2/diary/__init__.py
ch2/diary/database.py
ch2/diary/model.py
ch2/diary/views/__init__.py
ch2/diary/views/web.py
ch2/fit/__init__.py
ch2/fit/fix.py
ch2/fit/summary.py
ch2/fit/download/__init__.py
ch2/fit/download/connect.py
ch2/fit/format/__init__.py
ch2/fit/format/read.py
ch2/fit/format/records.py
ch2/fit/format/tokens.py
ch2/fit/profile/__init__.py
ch2/fit/profile/fields.py
choochoo-0.41.1.dist-info/METADATA
choochoo-0.41.1.dist-info/WHEEL
choochoo-0.41.1.dist-info/entry_points.txt
choochoo-0.41.1.dist-info/top_level.txt
choochoo-0.41.1.dist-info/RECORD
