Metadata-Version: 2.1
Name: choochoo
Version: 0.41.1
Summary: Data Science for Training
Home-page: https://github.com/andrewcooke/choochoo
Author: andrew cooke
Author-email: andrew@acooke.org
License: UNKNOWN
Platform: UNKNOWN
Classifier: Programming Language :: Python :: 3.9
Classifier: License :: OSI Approved :: GNU General Public License v3 (GPLv3)
Classifier: Operating System :: OS Independent
Classifier: Development Status :: 4 - Beta
Requires-Dist: bokeh
Requires-Dist: cachetools
Requires-Dist: colorama
Requires-Dist: colorlog
Requires-Dist: geoalchemy2
Requires-Dist: jupyter
Requires-Dist: matplotlib
Requires-Dist: numpy
Requires-Dist: openpyxl
Requires-Dist: pandas
Requires-Dist: pendulum
Requires-Dist: psutil
Requires-Dist: psycopg2
Requires-Dist: pyGeoTile
Requires-Dist: pyproj
Requires-Dist: rasterio
Requires-Dist: requests
Requires-Dist: scipy
Requires-Dist: shapely
Requires-Dist: sklearn
Requires-Dist: sqlalchemy-utils
Requires-Dist: sqlalchemy
Requires-Dist: uritools
Requires-Dist: werkzeug
